examples/graph_3d.zarr/tracks/.zattrs
examples/graph_3d.zarr/tracks/.zgroup
examples/graph_3d.zarr/tracks/edges/.zgroup
examples/graph_3d.zarr/tracks/edges/ids/.zarray
examples/graph_3d.zarr/tracks/edges/ids/0.0
examples/graph_3d.zarr/tracks/edges/ids/1.0
examples/graph_3d.zarr/tracks/nodes/.zgroup
examples/graph_3d.zarr/tracks/nodes/ids/.zarray
examples/graph_3d.zarr/tracks/nodes/ids/0
examples/graph_3d.zarr/tracks/nodes/ids/1
examples/graph_3d.zarr/tracks/nodes/props/.zgroup
examples/graph_3d.zarr/tracks/nodes/props/t/.zgroup
examples/graph_3d.zarr/tracks/nodes/props/t/values/.zarray
examples/graph_3d.zarr/tracks/nodes/props/t/values/0
examples/graph_3d.zarr/tracks/nodes/props/t/values/1
examples/graph_3d.zarr/tracks/nodes/props/track_id/.zgroup
examples/graph_3d.zarr/tracks/nodes/props/track_id/missing/.zarray
examples/graph_3d.zarr/tracks/nodes/props/track_id/missing/0
examples/graph_3d.zarr/tracks/nodes/props/track_id/values/.zarray
examples/graph_3d.zarr/tracks/nodes/props/track_id/values/0
examples/graph_3d.zarr/tracks/nodes/props/track_id/values/1
examples/graph_3d.zarr/tracks/nodes/props/x/.zgroup
examples/graph_3d.zarr/tracks/nodes/props/x/values/.zarray
examples/graph_3d.zarr/tracks/nodes/props/x/values/0
examples/graph_3d.zarr/tracks/nodes/props/x/values/1
examples/graph_3d.zarr/tracks/nodes/props/y/.zgroup
examples/graph_3d.zarr/tracks/nodes/props/y/values/.zarray
examples/graph_3d.zarr/tracks/nodes/props/y/values/0
examples/graph_3d.zarr/tracks/nodes/props/y/values/1
examples/graph_3d.zarr/tracks/nodes/props/z/.zgroup
examples/graph_3d.zarr/tracks/nodes/props/z/values/.zarray
examples/graph_3d.zarr/tracks/nodes/props/z/values/0
examples/graph_3d.zarr/tracks/nodes/props/z/values/1
examples/graph_labels_seg.zarr/zarr.json
examples/graph_labels_seg.zarr/image/zarr.json
examples/graph_labels_seg.zarr/image/c/0/0/0
examples/graph_labels_seg.zarr/image/c/1/0/0
examples/graph_labels_seg.zarr/labels/zarr.json
examples/graph_labels_seg.zarr/labels/c/0/0/0
napari_geff-0.0.3.dist-info/licenses/LICENSE
napari_geff-0.0.3.dist-info/METADATA
napari_geff-0.0.3.dist-info/WHEEL
napari_geff-0.0.3.dist-info/entry_points.txt
napari_geff-0.0.3.dist-info/top_level.txt
napari_geff-0.0.3.dist-info/RECORD
